atoot/__init__.py
atoot/api.py
atoot-1.0.2.dist-info/LICENSE
atoot-1.0.2.dist-info/METADATA
atoot-1.0.2.dist-info/WHEEL
atoot-1.0.2.dist-info/top_level.txt
atoot-1.0.2.dist-info/RECORD
